
[
    {
      "front": "平安",
      "back": {
        "拼音": "píng ān",
        "词义": "没有灾祸，没有不安",
        "用法": "我们祝愿祖国永远平安。"
      }
    },
    {
      "front": "寂静",
      "back": {
        "拼音": "jì jìng",
        "词义": "没有声音",
        "用法": "夜晚的森林是如此寂静。"
      }
    },
    {
      "front": "平静",
      "back": {
        "拼音": "píng jìng",
        "词义": "没有波澜",
        "用法": "湖面波光粼粼，风平浪静。"
      }
    },
    {
      "front": "平常",
      "back": {
        "拼音": "píng cháng",
        "词义": "不特别，不出奇",
        "用法": "他的生活很平常，每天上班下班。"
      }
    },
    {
        "front": "深奥",
        "back": {
          "拼音": "shēn ào",
          "词义": "难以理解的",
          "用法": "这道题太深奥了，我都看不懂。"
        }
      },
      {
        "front": "深沉",
        "back": {
          "拼音": "shēn chén",
          "词义": "不轻浮的，沉着的",
          "用法": "他是一个深沉的人，不善言辞。"
        }
      },
      {
        "front": "秘密",
        "back": {
          "拼音": "mì mì",
          "词义": "不为人知的",
          "用法": "这件事是我们的秘密，不能告诉别人。"
        }
      },
      {
        "front": "浅显",
        "back": {
          "拼音": "qiǎn xiǎn",
          "词义": "容易理解的",
          "用法": "这道题很浅显，小孩子都能做。"
        }
        },
        {
            "front": "不言而喻",
            "back": {
              "拼音": "bù yán ér yù",
              "词义": "显而易见，不必多说",
              "用法": "这是一个不言而喻的道理。"
            }
          },
          {
            "front": "战争",
            "back": {
              "拼音": "zhàn zhēng",
              "词义": "两个或多个国家、民族或集团之间为了争夺利益而进行的武装冲突",
              "用法": "战争是人类的灾难。"
            }
          },
          {
            "front": "战胜",
            "back": {
              "拼音": "zhàn shèng",
              "词义": "在战争中取得胜利",
              "用法": "我们战胜了敌人，取得了胜利。"
            }
          },
          {
            "front": "胜利",
            "back": {
              "拼音": "shèng lì",
              "词义": "在战争、比赛或其他竞赛中取得成功",
              "用法": "我们取得了胜利，为祖国争光。"
            }
          },
          {
            "front": "致胜",
            "back": {
              "拼音": "zhì shèng",
              "词义": "使取得胜利",
              "用法": "我们要努力奋斗，致胜于未来。"
            }
          },
          {
            "front": "赋予",
            "back": {
              "拼音": "fù yǔ",
              "词义": "给予",
              "用法": "上帝赋予了人类智慧和创造力。"
            }
          },
          {
            "front": "天赋",
            "back": {
              "拼音": "tiān fù",
              "词义": "与生俱来的才能",
              "用法": "他天赋异禀，在音乐方面有着极高的造诣。"
            }
          },
          {
            "front": "禀赋",
            "back": {
              "拼音": "bǐng fù",
              "词义": "天性所赋予的才能",
              "用法": "他禀赋不凡，在学业上取得了优异的成绩。"
            }
          },
          {
            "front": "创作",
            "back": {
              "拼音": "chuàng zuò ",
              "词义": "创造出新事物",
              "用法": "他创作了许多优秀的文学作品。"
            }
          },
          {
            "front": "收到",
            "back": {
              "拼音": "shōu dào",
              "词义": "接到",
              "用法": "他收到了一份意外的礼物。"
            }
          },
          {
            "front": "收获",
            "back": {
              "拼音": "shōu huò",
              "词义": "获得",
              "用法": "他通过努力学习，收获了丰硕的成果。"
            }
          },
          {
            "front": "拥护",
            "back": {
              "拼音": "yōng hù",
              "词义": "支持",
              "用法": "他拥护着正义和真理。"
            }
          },
          {
            "front": "拥挤",
            "back": {
              "拼音": "yōng jǐ",
              "词义": "人或物聚集在一起，空间狭窄",
              "用法": "地铁上非常拥挤，人们只能挤在一起。"
            }
          },
          {
            "front": "输送",
            "back": {
              "拼音": "shū sòng",
              "词义": "运输",
              "用法": "这条铁路将输送大量的货物。"
            }
          },
          {
            "front": "发送",
            "back": {
              "拼音": "fā sòng",
              "词义": "送出",
              "用法": "他发送了一封电子邮件给朋友。"
            }
          },
          {
            "front": "滋养",
            "back": {
              "拼音": "zī yǎng",
              "词义": "给予营养",
              "用法": "母亲的爱滋养了孩子的成长。"
            }
          },
          {
            "front": "滋生",
            "back": {
              "拼音": "zī shēng",
              "词义": "产生",
              "用法": "腐烂的食物会滋生细菌。"
            }
          },
          {
            "front": "满意",
            "back": {
              "拼音": "mǎn yì",
              "词义": "感到满足",
              "用法": "他对自己的工作感到满意。"
            }
          },
          {
            "front": "满足",
            "back": {
              "拼音": "mǎn zú",
              "词义": "达到要求",
              "用法": "他的要求很简单，只要我们能满足他就行了。"
            }
          }
      
  ]